odoo/addons/file_download/README.rst
odoo/addons/file_download/__init__.py
odoo/addons/file_download/__manifest__.py
odoo/addons/file_download/i18n/ca_ES.po
odoo/addons/file_download/i18n/es.po
odoo/addons/file_download/readme/CONTRIBUTORS.md
odoo/addons/file_download/readme/DESCRIPTION.md
odoo/addons/file_download/readme/USAGE.md
odoo/addons/file_download/security/ir.model.access.csv
odoo/addons/file_download/static/description/icon.png
odoo/addons/file_download/static/description/index.html
odoo/addons/file_download/tests/__init__.py
odoo/addons/file_download/tests/test_file_download.py
odoo/addons/file_download/tests/models/report.py
odoo/addons/file_download/wizard/__init__.py
odoo/addons/file_download/wizard/download_file.py
odoo/addons/file_download/wizard/download_file_view.xml
odoo_addon_file_download-17.0.1.0.0.1.dist-info/METADATA
odoo_addon_file_download-17.0.1.0.0.1.dist-info/WHEEL
odoo_addon_file_download-17.0.1.0.0.1.dist-info/top_level.txt
odoo_addon_file_download-17.0.1.0.0.1.dist-info/RECORD
