Metadata-Version: 2.1
Name: odoo-addon-file_download
Version: 17.0.1.0.0.1
Requires-Python: >=3.10
Requires-Dist: odoo>=17.0a,<17.1dev
Requires-Dist: odoo_test_helper
Summary: Download file
Home-page: https://github.com/sygel-technology/sy-server-backend
License: AGPL-3
Author: Sygel
Classifier: Programming Language :: Python
Classifier: Framework :: Odoo
Classifier: Framework :: Odoo :: 17.0
Classifier: License :: OSI Approved :: GNU Affero General Public License v3
